CHANGELOG.rst
databricks_api/__init__.py
databricks_api/_stubs.py
databricks_api/_version.py
databricks_api/databricks.py
databricks_api/databricks.pyi
databricks_api-0.8.0.dist-info/LICENSE.txt
databricks_api-0.8.0.dist-info/WHEEL
databricks_api-0.8.0.dist-info/METADATA
databricks_api-0.8.0.dist-info/RECORD
