Metadata-Version: 2.1
Name: databricks-api
Version: 0.8.0
Summary: Databricks API client auto-generated from the official databricks-cli package
Home-page: https://github.com/crflynn/databricks-api
License: MIT
Keywords: databricks,api,client
Author: Christopher Flynn
Author-email: crf204@gmail.com
Requires-Python: >=3.6,<4.0
Classifier: License :: OSI Approved :: MIT License
Classifier: Natural Language :: English
Classifier: Programming Language :: Python :: 2
Classifier: Programming Language :: Python :: 2.7
Classifier: Programming Language :: Python :: 3
Classifier: Programming Language :: Python :: 3.10
Classifier: Programming Language :: Python :: 3.5
Classifier: Programming Language :: Python :: 3.6
Classifier: Programming Language :: Python :: 3.7
Classifier: Programming Language :: Python :: 3.8
Classifier: Programming Language :: Python :: 3.9
Classifier: Programming Language :: Python :: Implementation :: CPython
Requires-Dist: databricks-cli
Project-URL: Repository, https://github.com/crflynn/databricks-api
